gQiwiAPI/__init__.py
gQiwiAPI/api.py
gQiwiAPI-1.4.7.dist-info/LICENSE
gQiwiAPI-1.4.7.dist-info/METADATA
gQiwiAPI-1.4.7.dist-info/WHEEL
gQiwiAPI-1.4.7.dist-info/top_level.txt
gQiwiAPI-1.4.7.dist-info/RECORD
