Metadata-Version: 2.1
Name: gQiwiAPI
Version: 1.4.7
Summary: A simple API for creating a payment link
Home-page: https://github.com/gnifajio/gQiwiAPI
Author: Gnifajio None
Author-email: gnifajio@gmail.com
Classifier: Programming Language :: Python :: 3.10
Classifier: License :: OSI Approved :: MIT License
Classifier: Operating System :: OS Independent
Requires-Python: >=3.7
License-File: LICENSE
